[
  {
    "id": "cd2f1515-ea2a-4abf-8bda-0815c473936f",
    "job_id": "09ca70b1-cafe-46fd-b421-6b5cf5676ea1",
    "timestamp": "2025-09-03T12:51:59.686503",
    "status_code": 200,
    "execution_time": 0.442,
    "success": true,
    "error_message": null
  },
  {
    "id": "1e437be3-3f91-48c5-9acd-a0dc5092223a",
    "job_id": "09ca70b1-cafe-46fd-b421-6b5cf5676ea1",
    "timestamp": "2025-09-03T12:55:02.394251",
    "status_code": 200,
    "execution_time": 0.449,
    "success": true,
    "error_message": null
  }
]